iSponsorBlockTV/__init__.py
iSponsorBlockTV/__main__.py
iSponsorBlockTV/api_helpers.py
iSponsorBlockTV/conditional_ttl_cache.py
iSponsorBlockTV/config_setup.py
iSponsorBlockTV/constants.py
iSponsorBlockTV/debug_helpers.py
iSponsorBlockTV/dial_client.py
iSponsorBlockTV/helpers.py
iSponsorBlockTV/main.py
iSponsorBlockTV/setup-wizard-style.tcss
iSponsorBlockTV/setup_wizard.py
iSponsorBlockTV/ytlounge.py
isponsorblocktv-2.6.1.dist-info/METADATA
isponsorblocktv-2.6.1.dist-info/WHEEL
isponsorblocktv-2.6.1.dist-info/entry_points.txt
isponsorblocktv-2.6.1.dist-info/licenses/LICENSE.md
isponsorblocktv-2.6.1.dist-info/RECORD
