Metadata-Version: 2.4
Name: iSponsorBlockTV
Version: 2.6.1
Summary: SponsorBlock client for all YouTube TV clients
Project-URL: Homepage, https://github.com/dmunozv04/iSponsorBlockTV
Project-URL: Bug Tracker, https://github.com/dmunozv04/iSponsorBlockTV/issues
Author: dmunozv04
License-File: LICENSE.md
Classifier: License :: OSI Approved :: GNU General Public License v3 (GPLv3)
Classifier: Operating System :: OS Independent
Classifier: Programming Language :: Python :: 3
Classifier: Topic :: Home Automation
Requires-Python: >=3.9
Requires-Dist: aiohttp==3.12.15
Requires-Dist: appdirs==1.4.4
Requires-Dist: async-cache==1.1.1
Requires-Dist: pyytlounge==2.3.0
Requires-Dist: rich-click==1.8.9
Requires-Dist: rich==14.1.0
Requires-Dist: ssdp==1.3.1
Requires-Dist: textual-slider==0.2.0
Requires-Dist: textual==5.3.0
Requires-Dist: xmltodict==0.15.1
